Metadata-Version: 2.1
Name: odoo-addon-purchase_stock_secondary_unit
Version: 17.0.1.0.0.5
Requires-Python: >=3.10
Requires-Dist: odoo-addon-purchase_order_secondary_unit>=17.0dev,<17.1dev
Requires-Dist: odoo-addon-stock_secondary_unit>=17.0dev,<17.1dev
Requires-Dist: odoo>=17.0a,<17.1dev
Summary: Get product quantities in a secondary unit
Home-page: https://github.com/OCA/purchase-workflow
License: AGPL-3
Author: Jarsa, Odoo Community Association (OCA)
Author-email: support@odoo-community.org
Classifier: Programming Language :: Python
Classifier: Framework :: Odoo
Classifier: Framework :: Odoo :: 17.0
Classifier: License :: OSI Approved :: GNU Affero General Public License v3
Classifier: Development Status :: 4 - Beta
